python_should_check-0.0.3.dist-info/METADATA
python_should_check-0.0.3.dist-info/RECORD
python_should_check-0.0.3.dist-info/WHEEL
python_should_check-0.0.3.dist-info/top_level.txt
should_check/__init__.py
should_check/check.py
should_check/should.py
