Metadata-Version: 2.1
Name: python-should-check
Version: 0.0.3
Summary: Exception factory
Home-page: https://github.com/SSHcom/python-should-check
Author: Pauli Rikula
License: MIT
Platform: UNKNOWN
Classifier: License :: OSI Approved :: MIT License
Classifier: Programming Language :: Python :: 3.6
Requires-Python: ~=3.6
